{
  "characters": [
    { "name": "Aang", "img": "placeholder" },
    { "name": "Katara", "img": "placeholder" },
    { "name": "Sokka", "img": "placeholder" },
    { "name": "Toph Beifong", "img": "placeholder" },
    { "name": "Zuko", "img": "placeholder" },
    { "name": "Appa", "img": "placeholder" },
    { "name": "Momo", "img": "placeholder" },
    { "name": "Fire Lord Ozai", "img": "placeholder" },
    { "name": "Azula", "img": "placeholder" },
    { "name": "Iroh", "img": "placeholder" },
    { "name": "Mai", "img": "placeholder" },
    { "name": "Ty Lee", "img": "placeholder" },
    { "name": "Zhao", "img": "placeholder" },
    { "name": "Ozai's Advisors: Long Feng and the Dai Li", "img": "placeholder" },
    { "name": "Chief Hakoda", "img": "placeholder" },
    { "name": "Chief Arnook", "img": "placeholder" },
    { "name": "Yue", "img": "placeholder" },
    { "name": "Master Pakku", "img": "placeholder" },
    { "name": "Hama", "img": "placeholder" },
    { "name": "King Bumi", "img": "placeholder" },
    { "name": "General Fong", "img": "placeholder" },
    { "name": "Haru", "img": "placeholder" },
    { "name": "Jet", "img": "placeholder" },
    { "name": "Longshot", "img": "placeholder" },
    { "name": "Smellerbee", "img": "placeholder" },
    { "name": "Guru Pathik", "img": "placeholder" },
    { "name": "June", "img": "placeholder" },
    { "name": "Cabbage Merchant", "img": "placeholder" },
    { "name": "Earth King Kuei", "img": "placeholder" },
    { "name": "Earth Queen Hou-Ting", "img": "placeholder" },
    { "name": "White Lotus Society members (including Iroh and Piandao)", "img": "placeholder" }
  ]
}
