{
  "items": [
    {
      "name": "Homer Simpson",
      "img": "placeholder"
    },
    {
      "name": "Marge Simpson",
      "img": "placeholder"
    },
    {
      "name": "Bart Simpson",
      "img": "placeholder"
    },
    {
      "name": "Lisa Simpson",
      "img": "placeholder"
    },
    {
      "name": "Maggie Simpson",
      "img": "placeholder"
    },
    {
      "name": "Abraham \"Grampa\" Simpson",
      "img": "placeholder"
    },
    {
      "name": "Ned Flanders",
      "img": "placeholder"
    },
    {
      "name": "Maude Flanders (formerly)",
      "img": "placeholder"
    },
    {
      "name": "Krusty the Clown",
      "img": "placeholder"
    },
    {
      "name": "Sideshow Bob",
      "img": "placeholder"
    },
    {
      "name": "Moe Szyslak",
      "img": "placeholder"
    },
    {
      "name": "Barney Gumble",
      "img": "placeholder"
    },
    {
      "name": "Lenny Leonard",
      "img": "placeholder"
    },
    {
      "name": "Carl Carlson",
      "img": "placeholder"
    },
    {
      "name": "Chief Clancy Wiggum",
      "img": "placeholder"
    },
    {
      "name": "Ralph Wiggum",
      "img": "placeholder"
    },
    {
      "name": "Apu Nahasapeemapetilon",
      "img": "placeholder"
    },
    {
      "name": "Milhouse Van Houten",
      "img": "placeholder"
    },
    {
      "name": "Nelson Muntz",
      "img": "placeholder"
    },
    {
      "name": "Jimbo Jones",
      "img": "placeholder"
    },
    {
      "name": "Kearney Zzyzwicz",
      "img": "placeholder"
    },
    {
      "name": "Mr. Burns",
      "img": "placeholder"
    },
    {
      "name": "Waylon Smithers",
      "img": "placeholder"
    },
    {
      "name": "Patty Bouvier",
      "img": "placeholder"
    },
    {
      "name": "Selma Bouvier",
      "img": "placeholder"
    },
    {
      "name": "Comic Book Guy",
      "img": "placeholder"
    },
    {
      "name": "Professor Frink",
      "img": "placeholder"
    },
    {
      "name": "Principal Seymour Skinner",
      "img": "placeholder"
    },
    {
      "name": "Superintendent Gary Chalmers",
      "img": "placeholder"
    },
    {
      "name": "Reverend Timothy Lovejoy",
      "img": "placeholder"
    },
    {
      "name": "Ned's Kids: Rod and Todd Flanders",
      "img": "placeholder"
    },
    {
      "name": "Dr. Hibbert",
      "img": "placeholder"
    },
    {
      "name": "Lunchlady Doris",
      "img": "placeholder"
    },
    {
      "name": "Sideshow Mel",
      "img": "placeholder"
    },
    {
      "name": "Fat Tony",
      "img": "placeholder"
    },
    {
      "name": "Snake Jailbird",
      "img": "placeholder"
    },
    {
      "name": "Hans Moleman",
      "img": "placeholder"
    },
    {
      "name": "Gil Gunderson",
      "img": "placeholder"
    },
    {
      "name": "Mayor Joe Quimby",
      "img": "placeholder"
    },
    {
      "name": "Bumblebee Man",
      "img": "placeholder"
    },
    {
      "name": "Cletus Spuckler",
      "img": "placeholder"
    },
    {
      "name": "Disco Stu",
      "img": "placeholder"
    },
    {
      "name": "Mrs. Krabappel (formerly)",
      "img": "placeholder"
    },
    {
      "name": "Groundskeeper Willie",
      "img": "placeholder"
    },
    {
      "name": "The Rich Texan",
      "img": "placeholder"
    },
    {
      "name": "Jasper Beardly",
      "img": "placeholder"
    },
    {
      "name": "Kent Brockman",
      "img": "placeholder"
    },
    {
      "name": "Mayor \"Diamond\" Joe Quimby",
      "img": "placeholder"
    },
    {
      "name": "Lionel Hutz (formerly)",
      "img": "placeholder"
    },
    {
      "name": "Troy McClure (formerly)",
      "img": "placeholder"
    }
  ]
}
